{
	"P001" : {"name" : "Paneer Soya Supreme", "price" : 545, "description" : "These are some ingredients"},
	"P002" : {"name" : "Veg Exotica", "price" : 545, "description" : "These are some ingredients"},
	"P003" : {"name" : "Veggie Italiano", "price" : 545, "description" : "These are some ingredients"},
	"P004" : {"name" : "Veggie Supreme", "price" : 545, "description" : "These are some ingredients"},
	"P005" : {"name" : "Chicken Exotica", "price" : 625, "description" : "These are some ingredients"},
	"P006" : {"name" : "Chicken Italiano", "price" : 625, "description" : "These are some ingredients"},
	"P007" : {"name" : "Chicken Supreme", "price" : 625, "description" : "These are some ingredients"},
	"P008" : {"name" : "Triple Chicken Feast", "price" : 625, "description" : "These are some ingredients"},
	"P009" : {"name" : "Country Feast", "price" : 515, "description" : "These are some ingredients"},
	"P010" : {"name" : "Farmers Pick", "price" : 515, "description" : "These are some ingredients"},
	"P011" : {"name" : "Tandoori Paneer", "price" : 515, "description" : "These are some ingredients"},
	"P012" : {"name" : "Veggie Lover", "price" : 515, "description" : "These are some ingredients"},
	"P013" : {"name" : "Chicken Sausage N Tikka", "price" : 545, "description" : "These are some ingredients"},
	"P014" : {"name" : "Chicken Tikka", "price" : 545, "description" : "These are some ingredients"},
	"P015" : {"name" : "Smoked Chicken", "price" : 545, "description" : "These are some ingredients"}
}
